Metadata-Version: 2.1
Name: omim-pytraffic
Version: 10.3.0rc2
Summary: Binding for generation traffic data for maps.me application
Home-page: https://github.com/mapsme/omim
Author: My.com B.V. (Mail.Ru Group)
Author-email: dev@maps.me
License: Apache-2.0
Platform: UNKNOWN
Classifier: License :: OSI Approved :: Apache Software License
Classifier: Programming Language :: Python
Classifier: Programming Language :: Python :: Implementation :: CPython
Classifier: Programming Language :: Python :: 2
Classifier: Programming Language :: Python :: 2.7
Classifier: Programming Language :: Python :: 3
Classifier: Programming Language :: Python :: 3.5
Classifier: Programming Language :: Python :: 3.6
Classifier: Programming Language :: Python :: 3.7
Classifier: Programming Language :: Python :: 3.8
Classifier: Programming Language :: Python :: 3.9
Requires-Dist: omim-data-essential (==10.3.0rc2)
